{"cameraMode":{"drawMode":0,"name":"Shaded","section":"Shading Mode"},"sceneLighting":true,"audioPlay":false,"sceneViewState":{"showFog":true,"showMaterialUpdate":false,"showSkybox":true,"showFlares":true,"showImageEffects":true,"showParticleSystems":true},"in2DMode":false,"pivot":{"x":984.0971069335938,"y":544.9180908203125,"z":1449.842529296875},"rotation":{"x":0.040488939732313159,"y":0.0014990214258432389,"z":-0.00006073820259189233,"w":0.9991788864135742},"size":3984.67333984375,"orthographic":false}